odoo/addons/connector_importer_product/README.rst
odoo/addons/connector_importer_product/__init__.py
odoo/addons/connector_importer_product/__manifest__.py
odoo/addons/connector_importer_product/components/__init__.py
odoo/addons/connector_importer_product/components/common.py
odoo/addons/connector_importer_product/components/product_supplierinfo.py
odoo/addons/connector_importer_product/components/product_product/__init__.py
odoo/addons/connector_importer_product/components/product_product/mapper.py
odoo/addons/connector_importer_product/components/product_product/record_handler.py
odoo/addons/connector_importer_product/data/import_type.xml
odoo/addons/connector_importer_product/demo/import_backend.xml
odoo/addons/connector_importer_product/demo/import_recordset.xml
odoo/addons/connector_importer_product/demo/import_source.xml
odoo/addons/connector_importer_product/i18n/connector_importer_product.pot
odoo/addons/connector_importer_product/i18n/it.po
odoo/addons/connector_importer_product/readme/CONTRIBUTORS.md
odoo/addons/connector_importer_product/readme/DESCRIPTION.md
odoo/addons/connector_importer_product/readme/ROADMAP.md
odoo/addons/connector_importer_product/static/description/icon.png
odoo/addons/connector_importer_product/static/description/index.html
odoo/addons/connector_importer_product/tests/__init__.py
odoo/addons/connector_importer_product/tests/common.py
odoo/addons/connector_importer_product/tests/test_product_attribute.py
odoo/addons/connector_importer_product/tests/test_product_category.py
odoo/addons/connector_importer_product/tests/test_product_packaging.py
odoo/addons/connector_importer_product/tests/test_product_product.py
odoo/addons/connector_importer_product/tests/test_record_handler.py
odoo/addons/connector_importer_product/tests/data/product_attribute.csv
odoo/addons/connector_importer_product/tests/data/product_attribute_value.csv
odoo/addons/connector_importer_product/tests/data/product_category.csv
odoo_addon_connector_importer_product-18.0.1.0.1.dist-info/METADATA
odoo_addon_connector_importer_product-18.0.1.0.1.dist-info/WHEEL
odoo_addon_connector_importer_product-18.0.1.0.1.dist-info/top_level.txt
odoo_addon_connector_importer_product-18.0.1.0.1.dist-info/RECORD
