Metadata-Version: 2.1
Name: odoo-addon-connector_importer_product
Version: 18.0.1.0.1
Requires-Python: >=3.10
Requires-Dist: odoo-addon-connector_importer==18.0.*
Requires-Dist: odoo==18.0.*
Summary: Ease definition of product imports using `connector_importer`.
Home-page: https://github.com/OCA/connector-interfaces
License: AGPL-3
Author: Camptocamp, Odoo Community Association (OCA)
Author-email: support@odoo-community.org
Classifier: Programming Language :: Python
Classifier: Framework :: Odoo
Classifier: Framework :: Odoo :: 18.0
Classifier: License :: OSI Approved :: GNU Affero General Public License v3
